imagej/__init__.py
imagej/_java.py
imagej/convert.py
imagej/dims.py
imagej/doctor.py
imagej/images.py
imagej/stack.py
pyimagej-1.6.0.dist-info/LICENSE.txt
pyimagej-1.6.0.dist-info/METADATA
pyimagej-1.6.0.dist-info/WHEEL
pyimagej-1.6.0.dist-info/entry_points.txt
pyimagej-1.6.0.dist-info/top_level.txt
pyimagej-1.6.0.dist-info/RECORD
