Metadata-Version: 2.2
Name: pyimagej
Version: 1.6.0
Summary: Python wrapper for ImageJ
Author-email: ImageJ2 developers <ctrueden@wisc.edu>
License: Apache-2.0
Project-URL: homepage, https://github.com/imagej/pyimagej
Project-URL: documentation, https://pyimagej.readthedocs.io/
Project-URL: source, https://github.com/imagej/pyimagej
Project-URL: download, https://pypi.org/project/pyimagej/
Project-URL: tracker, https://github.com/imagej/pyimagej/issues
Keywords: java,imagej,imagej2,fiji
Platform: any
Classifier: Development Status :: 5 - Production/Stable
Classifier: Intended Audience :: Developers
Classifier: Intended Audience :: Education
Classifier: Intended Audience :: Science/Research
Classifier: Programming Language :: Python :: 3 :: Only
Classifier: Programming Language :: Python :: 3.8
Classifier: Programming Language :: Python :: 3.9
Classifier: Programming Language :: Python :: 3.10
Classifier: Programming Language :: Python :: 3.11
Classifier: Programming Language :: Python :: 3.12
Classifier: License :: OSI Approved :: Apache Software License
Classifier: Operating System :: Microsoft :: Windows
Classifier: Operating System :: Unix
Classifier: Operating System :: MacOS
Classifier: Topic :: Scientific/Engineering
Classifier: Topic :: Scientific/Engineering :: Image Processing
Classifier: Topic :: Scientific/Engineering :: Visualization
Classifier: Topic :: Software Development :: Libraries :: Java Libraries
Classifier: Topic :: Software Development :: Libraries :: Python Modules
Classifier: Topic :: Utilities
Requires-Python: >=3.8
License-File: LICENSE.txt
Requires-Dist: imglyb>=2.1.0
Requires-Dist: jgo>=1.0.3
Requires-Dist: jpype1>=1.3.0
Requires-Dist: labeling>=0.1.14
Requires-Dist: numpy
Requires-Dist: scyjava>=1.8.0
Requires-Dist: xarray
Provides-Extra: dev
Requires-Dist: build; extra == "dev"
Requires-Dist: myst-nb; extra == "dev"
Requires-Dist: pre-commit; extra == "dev"
Requires-Dist: pytest; extra == "dev"
Requires-Dist: pytest-cov; extra == "dev"
Requires-Dist: ruff; extra == "dev"
Requires-Dist: sphinx; extra == "dev"
Requires-Dist: sphinx_rtd_theme; extra == "dev"
Requires-Dist: validate-pyproject[all]; extra == "dev"
Provides-Extra: matplotlib
Requires-Dist: matplotlib; extra == "matplotlib"
Provides-Extra: notebooks
Requires-Dist: ipywidgets; extra == "notebooks"
Requires-Dist: jupyter_contrib_nbextensions; extra == "notebooks"
Requires-Dist: notebook<7.0.0; extra == "notebooks"
Requires-Dist: pooch; extra == "notebooks"
Requires-Dist: scikit-image; extra == "notebooks"
